{"mario":{"p":[0,2,0],"ry":-180},"objects":[{"a":279,"m":"koopa_model","s":0.008,"p":[-0.003,1.2,-1.689]},{"a":166,"m":"kb2_stage","s":0.008,"p":[0,0,0]},{"a":284,"m":"koopa_bomb","s":0.008,"p":[0,1.2,3.5]},{"a":284,"m":"koopa_bomb","s":0.008,"p":[3.5,1.2,0]},{"a":284,"m":"koopa_bomb","s":0.008,"p":[0,1.2,-3.5]},{"a":284,"m":"koopa_bomb","s":0.008,"p":[-3.5,1.2,0]},{"a":196,"p":[0,-0.5,0]},{"a":284,"m":"koopa_bomb","s":0.008,"p":[-2.475,1.2,-2.475]},{"a":284,"m":"koopa_bomb","s":0.008,"p":[-2.475,1.2,2.475]},{"a":284,"m":"koopa_bomb","s":0.008,"p":[2.475,1.2,2.475]},{"a":284,"m":"koopa_bomb","s":0.008,"p":[2.475,1.2,-2.475]}],"sky":"vr07"}