{
 "course": "old_baby_gc",
 "objects": [
  {
   "file": "MapObj-itembox.glb",
   "pos": [
    -17.812484741210938,
    37.49998474121094,
    -56.25
   ]
  },
  {
   "file": "MapObj-itembox.glb",
   "pos": [
    -8.437484741210938,
    37.5,
    -56.25
   ]
  },
  {
   "file": "MapObj-itembox.glb",
   "pos": [
    -20.937484741210938,
    37.49998474121094,
    -56.25
   ]
  },
  {
   "file": "MapObj-itembox.glb",
   "pos": [
    -11.562484741210938,
    37.5,
    -56.25
   ]
  },
  {
   "file": "MapObj-itembox.glb",
   "pos": [
    -14.687484741210938,
    37.5,
    -56.25
   ]
  },
  {
   "file": "MapObj-itembox.glb",
   "pos": [
    8.437484741210938,
    37.5,
    56.25
   ]
  },
  {
   "file": "MapObj-itembox.glb",
   "pos": [
    14.687484741210938,
    37.5,
    56.25
   ]
  },
  {
   "file": "MapObj-itembox.glb",
   "pos": [
    11.562484741210938,
    37.5,
    56.25
   ]
  },
  {
   "file": "MapObj-itembox.glb",
   "pos": [
    20.937484741210938,
    37.49998474121094,
    56.25
   ]
  },
  {
   "file": "MapObj-itembox.glb",
   "pos": [
    17.812484741210938,
    37.49998474121094,
    56.25
   ]
  }
 ],
 "skipped": {
  "0x008": 1
 },
 "space": "glb"
}