{
 "format": 2,
 "level": "tainai03",
 "objects": [
  {
   "id": 0,
   "name": "camera_areatrig_",
   "pos": [
    -886.3106,
    103.83557,
    -66
   ],
   "props": {
    "dag": "|grp_camera_offset|camera_areatrig_",
    "rotZ": 0,
    "scale": [
     1,
     1,
     1
    ]
   }
  },
  {
   "id": 1,
   "name": "chuppa",
   "pos": [
    2661,
    -595.7213,
    -35
   ],
   "props": {
    "dag": "chuppa",
    "rotZ": 0,
    "scale": [
     1,
     1,
     1
    ]
   }
  },
  {
   "id": 2,
   "name": "dbgmsg_demo",
   "pos": [
    -2583.7712,
    1269.0554,
    0
   ],
   "props": {
    "dag": "|grp_start_set|dbgmsg_demo",
    "rotZ": 0,
    "scale": [
     1,
     1,
     1
    ]
   }
  },
  {
   "id": 3,
   "name": "delay",
   "pos": [
    -0.573647,
    -10,
    0
   ],
   "props": {
    "dag": "delay",
    "rotZ": 0,
    "scale": [
     1,
     1,
     1
    ]
   }
  },
  {
   "id": 4,
   "name": "delay_bbb4",
   "pos": [
    -0.000003,
    0,
    98
   ],
   "props": {
    "dag": "|grp_chara|kunamama_1|delay_bbb4",
    "rotZ": 0,
    "scale": [
     1,
     1,
     1
    ]
   }
  },
  {
   "id": 5,
   "name": "delay_open2muising",
   "pos": [
    -1800,
    -1193.0295,
    0
   ],
   "props": {
    "dag": "|grp_start_set|grp_muising|delay_open2muising",
    "rotZ": 0,
    "scale": [
     1,
     1,
     1
    ]
   }
  },
  {
   "id": 6,
   "name": "kcoin_item",
   "pos": [
    2023.4241,
    -446.97516,
    49
   ],
   "props": {
    "dag": "kcoin_item",
    "rotZ": 0,
    "scale": [
     1,
     1,
     1
    ]
   }
  },
  {
   "id": 7,
   "name": "kitem_mushi_muimui",
   "pos": [
    -2210,
    -43.872803,
    49
   ],
   "props": {
    "dag": "|grp_muimui|grp_muimui_2|kitem_mushi_muimui",
    "rotZ": 0,
    "scale": [
     1,
     1,
     1
    ]
   }
  },
  {
   "id": 8,
   "name": "kitem_mushi_muimui",
   "pos": [
    -1990.4204,
    744.3345,
    149
   ],
   "props": {
    "dag": "|grp_muimui_1|kitem_mushi_muimui",
    "rotZ": 0,
    "scale": [
     1,
     1,
     1
    ]
   }
  },
  {
   "id": 9,
   "name": "kunamama",
   "pos": [
    -1649.4486,
    19.190552,
    -15
   ],
   "props": {
    "dag": "kunamama",
    "rotZ": 0,
    "scale": [
     1,
     1,
     1
    ]
   }
  },
  {
   "id": 10,
   "name": "mi_one_kakushi_2",
   "pos": [
    1475.6438,
    -942.5873,
    -29.999996
   ],
   "props": {
    "dag": "|mi_one_kakushi_2",
    "rotZ": 0,
    "scale": [
     1,
     1,
     1
    ]
   }
  },
  {
   "id": 11,
   "name": "mojya",
   "pos": [
    1212.7471,
    -921,
    -15
   ],
   "props": {
    "dag": "mojya",
    "rotZ": 0,
    "scale": [
     1,
     1,
     1
    ]
   }
  },
  {
   "id": 12,
   "name": "mojya_3",
   "pos": [
    1029,
    -921,
    -15
   ],
   "props": {
    "dag": "|grp_chara|mojya_3",
    "rotZ": 0,
    "scale": [
     1,
     1,
     1
    ]
   }
  },
  {
   "id": 13,
   "name": "mojya_4",
   "pos": [
    2261,
    -600.48083,
    -35
   ],
   "props": {
    "dag": "|grp_chara|mojya_4",
    "rotZ": 0,
    "scale": [
     1,
     1,
     1
    ]
   }
  },
  {
   "id": 14,
   "name": "muimui",
   "pos": [
    2023.1992,
    -429.87067,
    0
   ],
   "props": {
    "dag": "muimui",
    "rotZ": 0,
    "scale": [
     1,
     1,
     1
    ]
   }
  },
  {
   "id": 15,
   "name": "muimui_2",
   "pos": [
    -2210.2246,
    -26.76831,
    0
   ],
   "props": {
    "dag": "|grp_muimui|grp_muimui_2|muimui_2",
    "rotZ": 0,
    "scale": [
     1,
     1,
     1
    ]
   }
  },
  {
   "id": 16,
   "name": "muimui_3",
   "pos": [
    -1990.645,
    761.43896,
    100
   ],
   "props": {
    "dag": "|grp_muimui_1|muimui_3",
    "rotZ": 0,
    "scale": [
     1,
     1,
     1
    ]
   }
  },
  {
   "id": 17,
   "name": "poly_trigger",
   "pos": [
    0.096858,
    0,
    0
   ],
   "props": {
    "dag": "poly_trigger",
    "rotZ": 0,
    "scale": [
     1,
     1,
     1
    ]
   }
  },
  {
   "id": 18,
   "name": "polytrig_kakushi",
   "pos": [
    0.096858,
    0,
    0
   ],
   "props": {
    "dag": "|grp_hibi_set_1|kakushi_1|polytrig_kakushi",
    "rotZ": 0,
    "scale": [
     1,
     1,
     1
    ]
   }
  },
  {
   "id": 19,
   "name": "polytrig_kakushi",
   "pos": [
    0.096858,
    0,
    0
   ],
   "props": {
    "dag": "|grp_kakushi|kakushi_4|polytrig_kakushi",
    "rotZ": 0,
    "scale": [
     1,
     1,
     1
    ]
   }
  },
  {
   "id": 20,
   "name": "polytrig_kakushi",
   "pos": [
    0.096858,
    0,
    0
   ],
   "props": {
    "dag": "|grp_kakushi|kakushi_3|polytrig_kakushi",
    "rotZ": 0,
    "scale": [
     1,
     1,
     1
    ]
   }
  },
  {
   "id": 21,
   "name": "reference",
   "pos": [
    -1245.0588,
    8.622192,
    80
   ],
   "props": {
    "dag": "reference",
    "rotZ": 0,
    "scale": [
     1,
     1,
     1
    ]
   }
  },
  {
   "id": 22,
   "name": "reference_gameover",
   "pos": [
    -2498.6343,
    948.7429,
    0
   ],
   "props": {
    "dag": "|grp_start_set|reference_gameover",
    "rotZ": 0,
    "scale": [
     1,
     1,
     1
    ]
   }
  },
  {
   "id": 23,
   "name": "se_score4",
   "pos": [
    72.64662,
    -2.615,
    -3
   ],
   "props": {
    "dag": "|se_score4",
    "rotZ": 0.139626,
    "scale": [
     1,
     1,
     1
    ]
   }
  },
  {
   "id": 24,
   "name": "shukuhou",
   "pos": [
    43.0752,
    -18.152,
    -1
   ],
   "props": {
    "dag": "shukuhou",
    "rotZ": 0,
    "scale": [
     1,
     1,
     1
    ]
   }
  },
  {
   "id": 25,
   "name": "shukuhou01",
   "pos": [
    -61.27682,
    -8.712,
    -2
   ],
   "props": {
    "dag": "|shukuhou01",
    "rotZ": 0.33273,
    "scale": [
     1,
     1,
     1
    ]
   }
  },
  {
   "id": 26,
   "name": "shukuhou02",
   "pos": [
    -59.338066,
    -7.169,
    -3
   ],
   "props": {
    "dag": "|shukuhou02",
    "rotZ": 0,
    "scale": [
     1,
     1,
     1
    ]
   }
  },
  {
   "id": 27,
   "name": "shukuhou03",
   "pos": [
    77.36388,
    -3.37,
    -2
   ],
   "props": {
    "dag": "|shukuhou03",
    "rotZ": -0.191986,
    "scale": [
     1,
     1,
     1
    ]
   }
  },
  {
   "id": 28,
   "name": "waitbutton",
   "pos": [
    -2498.6343,
    928.7429,
    0
   ],
   "props": {
    "dag": "waitbutton",
    "rotZ": 0,
    "scale": [
     1,
     1,
     1
    ]
   }
  }
 ]
}
